dem/__init__.py
dem/__main__.py
dem/cli/command/add_cat_cmd.py
dem/cli/command/add_host_cmd.py
dem/cli/command/add_reg_cmd.py
dem/cli/command/add_task_cmd.py
dem/cli/command/assign_cmd.py
dem/cli/command/clone_cmd.py
dem/cli/command/cp_cmd.py
dem/cli/command/create_cmd.py
dem/cli/command/del_cat_cmd.py
dem/cli/command/del_host_cmd.py
dem/cli/command/del_reg_cmd.py
dem/cli/command/del_task_cmd.py
dem/cli/command/delete_cmd.py
dem/cli/command/export_cmd.py
dem/cli/command/import_cmd.py
dem/cli/command/info_cmd.py
dem/cli/command/init_cmd.py
dem/cli/command/install_cmd.py
dem/cli/command/list_cat_cmd.py
dem/cli/command/list_cmd.py
dem/cli/command/list_host_cmd.py
dem/cli/command/list_reg_cmd.py
dem/cli/command/list_tools_cmd.py
dem/cli/command/modify_cmd.py
dem/cli/command/rename_cmd.py
dem/cli/command/run_cmd.py
dem/cli/command/set_default_cmd.py
dem/cli/command/uninstall_cmd.py
dem/cli/console.py
dem/cli/main.py
dem/cli/tui/printable_tool_image.py
dem/cli/tui/renderable/menu.py
dem/cli/tui/tui_user_output.py
dem/cli/tui/window/dev_env_settings_window.py
dem/core/container_engine.py
dem/core/core.py
dem/core/data_management.py
dem/core/dev_env.py
dem/core/dev_env_catalog.py
dem/core/exceptions.py
dem/core/hosts.py
dem/core/platform.py
dem/core/properties.py
dem/core/registry.py
dem/core/tool_images.py
dem/core/user_output.py
axem_dem-0.8.0.dist-info/LICENSE
axem_dem-0.8.0.dist-info/METADATA
axem_dem-0.8.0.dist-info/WHEEL
axem_dem-0.8.0.dist-info/entry_points.txt
axem_dem-0.8.0.dist-info/RECORD
