Metadata-Version: 2.1
Name: axem-dem
Version: 0.8.0
Summary: Manager for Containerized Development Environments
Home-page: https://axemsolutions.io/
License: Eclipse Public License - v2.0
Keywords: iot,embedded,edge,development environment,tools,containers
Author: Janos Murai
Author-email: janos.murai@axemsolutions.io
Requires-Python: >=3.10,<4.0
Classifier: Development Status :: 3 - Alpha
Classifier: Environment :: Console
Classifier: Intended Audience :: Developers
Classifier: License :: Other/Proprietary License
Classifier: Natural Language :: English
Classifier: Programming Language :: Python :: 3
Classifier: Programming Language :: Python :: 3.10
Classifier: Programming Language :: Python :: 3.11
Classifier: Programming Language :: Python :: 3.12
Classifier: Programming Language :: Python :: 3.13
Classifier: Topic :: Software Development
Classifier: Topic :: Software Development :: Build Tools
Classifier: Topic :: Software Development :: Compilers
Classifier: Topic :: Software Development :: Debuggers
Classifier: Topic :: Software Development :: Embedded Systems
Classifier: Topic :: Software Development :: Testing
Requires-Dist: docker (>=7.0.0,<8.0.0)
Requires-Dist: readchar (>=4.0.6,<5.0.0)
Requires-Dist: requests (==2.31.0)
Requires-Dist: rich (>=13.7.1,<14.0.0)
Requires-Dist: truststore (>=0.10.0,<0.11.0)
Requires-Dist: typer (>=0.12.2,<0.13.0)
Project-URL: Documentation, https://axemsolutions.io/dem_doc/
Project-URL: Repository, https://github.com/axem-solutions/dem
